listpad/__init__.py
listpad/list_padder.py
listpad-0.0.2.dist-info/DESCRIPTION.rst
listpad-0.0.2.dist-info/METADATA
listpad-0.0.2.dist-info/RECORD
listpad-0.0.2.dist-info/WHEEL
listpad-0.0.2.dist-info/metadata.json
listpad-0.0.2.dist-info/top_level.txt
